iam_map/cli.py
iam_map/exporter.py
iam_map/graph_query.py
iam_map/ollama_client.py
iam_map/paths.py
iam_map-0.2.3.dist-info/METADATA
iam_map-0.2.3.dist-info/WHEEL
iam_map-0.2.3.dist-info/entry_points.txt
iam_map-0.2.3.dist-info/top_level.txt
iam_map-0.2.3.dist-info/RECORD
