Metadata-Version: 2.4
Name: iam-map
Version: 0.2.3
Summary: Offline IAM graph exporter + NLP query shell
Author-email: Hrishi Logani <loganihrishi@gmail.com>
Requires-Python: >=3.8
Requires-Dist: boto3
Requires-Dist: networkx
Requires-Dist: pydot
Requires-Dist: pyparsing>=3.0.9
Requires-Dist: rich
Requires-Dist: typer[all]
Requires-Dist: requests
